{
    "data": [
        {
            "traceID": "c0277f412c45ef0e51b0aa30b420a6c5",
            "spans": [
                {
                    "traceID": "c0277f412c45ef0e51b0aa30b420a6c5",
                    "spanID": "52734f9550cbfe6a",
                    "flags": 1,
                    "operationName": "Recv./",
                    "references": [],
                    "startTime": 1602134004969874,
                    "duration": 20523,
                    "tags": [
                        {
                            "key": "http.method",
                            "type": "string",
                            "value": "GET"
                        },
                        {
                            "key": "http.user_agent",
                            "type": "string",
                            "value": "kube-probe/1.16+"
                        },
                        {
                            "key": "http.path",
                            "type": "string",
                            "value": "/"
                        },
                        {
                            "key": "http.host",
                            "type": "string",
                            "value": ""
                        },
                        {
                            "key": "status.code",
                            "type": "int64",
                            "value": 0
                        },
                        {
                            "key": "status.message",
                            "type": "string",
                            "value": "\"OK\""
                        }
                    ],
                    "logs": [],
                    "processID": "p1",
                    "warnings": null
                },
                {
                    "traceID": "c0277f412c45ef0e51b0aa30b420a6c5",
                    "spanID": "1b88921a47423fbc",
                    "flags": 1,
                    "operationName": "Sent.hipstershop.CurrencyService.GetSupportedCurrencies",
                    "references": [
                        {
                            "refType": "CHILD_OF",
                            "traceID": "c0277f412c45ef0e51b0aa30b420a6c5",
                            "spanID": "52734f9550cbfe6a"
                        }
                    ],
                    "startTime": 1602134004969936,
                    "duration": 2199,
                    "tags": [
                        {
                            "key": "Client",
                            "type": "bool",
                            "value": true
                        },
                        {
                            "key": "FailFast",
                            "type": "bool",
                            "value": true
                        },
                        {
                            "key": "status.code",
                            "type": "int64",
                            "value": 0
                        },
                        {
                            "key": "status.message",
                            "type": "string",
                            "value": ""
                        }
                    ],
                    "logs": [],
                    "processID": "p1",
                    "warnings": null
                },
                {
                    "traceID": "c0277f412c45ef0e51b0aa30b420a6c5",
                    "spanID": "e49cd59f3db97f0d",
                    "flags": 1,
                    "operationName": "Sent.hipstershop.ProductCatalogService.ListProducts",
                    "references": [
                        {
                            "refType": "CHILD_OF",
                            "traceID": "c0277f412c45ef0e51b0aa30b420a6c5",
                            "spanID": "52734f9550cbfe6a"
                        }
                    ],
                    "startTime": 1602134004972165,
                    "duration": 6918,
                    "tags": [
                        {
                            "key": "Client",
                            "type": "bool",
                            "value": true
                        },
                        {
                            "key": "FailFast",
                            "type": "bool",
                            "value": true
                        },
                        {
                            "key": "status.code",
                            "type": "int64",
                            "value": 0
                        },
                        {
                            "key": "status.message",
                            "type": "string",
                            "value": ""
                        }
                    ],
                    "logs": [],
                    "processID": "p1",
                    "warnings": null
                },
                {
                    "traceID": "c0277f412c45ef0e51b0aa30b420a6c5",
                    "spanID": "adb118253430c05e",
                    "flags": 1,
                    "operationName": "Sent.hipstershop.CartService.GetCart",
                    "references": [
                        {
                            "refType": "CHILD_OF",
                            "traceID": "c0277f412c45ef0e51b0aa30b420a6c5",
                            "spanID": "52734f9550cbfe6a"
                        }
                    ],
                    "startTime": 1602134004979111,
                    "duration": 4133,
                    "tags": [
                        {
                            "key": "Client",
                            "type": "bool",
                            "value": true
                        },
                        {
                            "key": "FailFast",
                            "type": "bool",
                            "value": true
                        },
                        {
                            "key": "status.code",
                            "type": "int64",
                            "value": 0
                        },
                        {
                            "key": "status.message",
                            "type": "string",
                            "value": ""
                        }
                    ],
                    "logs": [],
                    "processID": "p1",
                    "warnings": null
                },
                {
                    "traceID": "c0277f412c45ef0e51b0aa30b420a6c5",
                    "spanID": "76c65baa2aa700b0",
                    "flags": 1,
                    "operationName": "Sent.hipstershop.CurrencyService.Convert",
                    "references": [
                        {
                            "refType": "CHILD_OF",
                            "traceID": "c0277f412c45ef0e51b0aa30b420a6c5",
                            "spanID": "52734f9550cbfe6a"
                        }
                    ],
                    "startTime": 1602134004983282,
                    "duration": 1937,
                    "tags": [
                        {
                            "key": "Client",
                            "type": "bool",
                            "value": true
                        },
                        {
                            "key": "FailFast",
                            "type": "bool",
                            "value": true
                        },
                        {
                            "key": "status.code",
                            "type": "int64",
                            "value": 0
                        },
                        {
                            "key": "status.message",
                            "type": "string",
                            "value": ""
                        }
                    ],
                    "logs": [],
                    "processID": "p1",
                    "warnings": null
                },
                {
                    "traceID": "c0277f412c45ef0e51b0aa30b420a6c5",
                    "spanID": "3fdb9e2f211e4101",
                    "flags": 1,
                    "operationName": "Sent.hipstershop.AdService.GetAds",
                    "references": [
                        {
                            "refType": "CHILD_OF",
                            "traceID": "c0277f412c45ef0e51b0aa30b420a6c5",
                            "spanID": "52734f9550cbfe6a"
                        }
                    ],
                    "startTime": 1602134004985243,
                    "duration": 5012,
                    "tags": [
                        {
                            "key": "Client",
                            "type": "bool",
                            "value": true
                        },
                        {
                            "key": "FailFast",
                            "type": "bool",
                            "value": true
                        },
                        {
                            "key": "status.code",
                            "type": "int64",
                            "value": 0
                        },
                        {
                            "key": "status.message",
                            "type": "string",
                            "value": ""
                        }
                    ],
                    "logs": [],
                    "processID": "p1",
                    "warnings": null
                },
                {
                    "traceID": "c0277f412c45ef0e51b0aa30b420a6c5",
                    "spanID": "1bb4ef5fe33ab13c",
                    "flags": 1,
                    "operationName": "Sent.hipstershop.AdService.GetAds",
                    "references": [
                        {
                            "refType": "CHILD_OF",
                            "traceID": "c0277f412c45ef0e51b0aa30b420a6c5",
                            "spanID": "7efacb3dd62c0b15"
                        }
                    ],
                    "startTime": 1602134004972934,
                    "duration": 5113,
                    "tags": [
                        {
                            "key": "Client",
                            "type": "bool",
                            "value": true
                        },
                        {
                            "key": "FailFast",
                            "type": "bool",
                            "value": true
                        },
                        {
                            "key": "status.code",
                            "type": "int64",
                            "value": 0
                        },
                        {
                            "key": "status.message",
                            "type": "string",
                            "value": ""
                        }
                    ],
                    "logs": [],
                    "processID": "p2",
                    "warnings": null
                },
                {
                    "traceID": "c0277f412c45ef0e51b0aa30b420a6c5",
                    "spanID": "7efacb3dd62c0b15",
                    "flags": 1,
                    "operationName": "Recv.hipstershop.ProductCatalogService.ListProducts",
                    "references": [
                        {
                            "refType": "CHILD_OF",
                            "traceID": "c0277f412c45ef0e51b0aa30b420a6c5",
                            "spanID": "e49cd59f3db97f0d"
                        }
                    ],
                    "startTime": 1602134004972841,
                    "duration": 5261,
                    "tags": [
                        {
                            "key": "Client",
                            "type": "bool",
                            "value": false
                        },
                        {
                            "key": "FailFast",
                            "type": "bool",
                            "value": false
                        },
                        {
                            "key": "status.code",
                            "type": "int64",
                            "value": 0
                        },
                        {
                            "key": "status.message",
                            "type": "string",
                            "value": ""
                        }
                    ],
                    "logs": [],
                    "processID": "p2",
                    "warnings": null
                },
                {
                    "traceID": "c0277f412c45ef0e51b0aa30b420a6c5",
                    "spanID": "98ada2ba4b3a0a4d",
                    "flags": 1,
                    "operationName": "Retrieve Ads",
                    "references": [
                        {
                            "refType": "CHILD_OF",
                            "traceID": "c0277f412c45ef0e51b0aa30b420a6c5",
                            "spanID": "cdfc23a8d15435a3"
                        }
                    ],
                    "startTime": 1602134004986207,
                    "duration": 1132,
                    "tags": [
                        {
                            "key": "method",
                            "type": "string",
                            "value": "getAds"
                        }
                    ],
                    "logs": [
                        {
                            "timestamp": 1602134004986246,
                            "fields": [
                                {
                                    "key": "description",
                                    "type": "string",
                                    "value": "No Context provided. Constructing random Ads."
                                }
                            ]
                        }
                    ],
                    "processID": "p3",
                    "warnings": null
                },
                {
                    "traceID": "c0277f412c45ef0e51b0aa30b420a6c5",
                    "spanID": "67b3ed995dcd8e4",
                    "flags": 1,
                    "operationName": "Recv.hipstershop.AdService.GetAds",
                    "references": [
                        {
                            "refType": "CHILD_OF",
                            "traceID": "c0277f412c45ef0e51b0aa30b420a6c5",
                            "spanID": "1bb4ef5fe33ab13c"
                        }
                    ],
                    "startTime": 1602134004974000,
                    "duration": 1632,
                    "tags": [],
                    "logs": [],
                    "processID": "p3",
                    "warnings": null
                },
                {
                    "traceID": "c0277f412c45ef0e51b0aa30b420a6c5",
                    "spanID": "7be056b969501036",
                    "flags": 1,
                    "operationName": "Retrieve Ads",
                    "references": [
                        {
                            "refType": "CHILD_OF",
                            "traceID": "c0277f412c45ef0e51b0aa30b420a6c5",
                            "spanID": "67b3ed995dcd8e4"
                        }
                    ],
                    "startTime": 1602134004974247,
                    "duration": 1138,
                    "tags": [
                        {
                            "key": "method",
                            "type": "string",
                            "value": "getAds"
                        }
                    ],
                    "logs": [
                        {
                            "timestamp": 1602134004974284,
                            "fields": [
                                {
                                    "key": "description",
                                    "type": "string",
                                    "value": "No Context provided. Constructing random Ads."
                                }
                            ]
                        }
                    ],
                    "processID": "p3",
                    "warnings": null
                },
                {
                    "traceID": "c0277f412c45ef0e51b0aa30b420a6c5",
                    "spanID": "cdfc23a8d15435a3",
                    "flags": 1,
                    "operationName": "Recv.hipstershop.AdService.GetAds",
                    "references": [
                        {
                            "refType": "CHILD_OF",
                            "traceID": "c0277f412c45ef0e51b0aa30b420a6c5",
                            "spanID": "3fdb9e2f211e4101"
                        }
                    ],
                    "startTime": 1602134004986000,
                    "duration": 1546,
                    "tags": [],
                    "logs": [],
                    "processID": "p3",
                    "warnings": null
                }
            ],
            "processes": {
                "p1": {
                    "serviceName": "frontend",
                    "tags": []
                },
                "p2": {
                    "serviceName": "productcatalogservice",
                    "tags": []
                },
                "p3": {
                    "serviceName": "adservice",
                    "tags": []
                }
            },
            "warnings": null
        }
    ],
    "total": 0,
    "limit": 0,
    "offset": 0,
    "errors": null
}